jikuai/__init__.py
jikuai/dataset.py
jikuai-0.0.12.dist-info/LICENSE
jikuai-0.0.12.dist-info/METADATA
jikuai-0.0.12.dist-info/WHEEL
jikuai-0.0.12.dist-info/top_level.txt
jikuai-0.0.12.dist-info/RECORD
